MANIFEST.in
README
setup.cfg
setup.py
../libdrqueue
/Users/jorge/prog/drqueue/libdrqueue/3delightsg.c
/Users/jorge/prog/drqueue/libdrqueue/3dsmaxsg.c
/Users/jorge/prog/drqueue/libdrqueue/aftereffectssg.c
/Users/jorge/prog/drqueue/libdrqueue/aqsissg.c
/Users/jorge/prog/drqueue/libdrqueue/blendersg.c
/Users/jorge/prog/drqueue/libdrqueue/cinema4dsg.c
/Users/jorge/prog/drqueue/libdrqueue/common.c
/Users/jorge/prog/drqueue/libdrqueue/communications.c
/Users/jorge/prog/drqueue/libdrqueue/computer.c
/Users/jorge/prog/drqueue/libdrqueue/computer_info.c
/Users/jorge/prog/drqueue/libdrqueue/computer_pool.c
/Users/jorge/prog/drqueue/libdrqueue/computer_status.c
/Users/jorge/prog/drqueue/libdrqueue/config.c
/Users/jorge/prog/drqueue/libdrqueue/database.c
/Users/jorge/prog/drqueue/libdrqueue/drerrno.c
/Users/jorge/prog/drqueue/libdrqueue/envvars.c
/Users/jorge/prog/drqueue/libdrqueue/generalsg.c
/Users/jorge/prog/drqueue/libdrqueue/job.c
/Users/jorge/prog/drqueue/libdrqueue/jobscript.c
/Users/jorge/prog/drqueue/libdrqueue/lightwavesg.c
/Users/jorge/prog/drqueue/libdrqueue/list.c
/Users/jorge/prog/drqueue/libdrqueue/logger.c
/Users/jorge/prog/drqueue/libdrqueue/luxrendersg.c
/Users/jorge/prog/drqueue/libdrqueue/mantrasg.c
/Users/jorge/prog/drqueue/libdrqueue/mayasg.c
/Users/jorge/prog/drqueue/libdrqueue/mentalraysg.c
/Users/jorge/prog/drqueue/libdrqueue/nukesg.c
/Users/jorge/prog/drqueue/libdrqueue/pixiesg.c
/Users/jorge/prog/drqueue/libdrqueue/pointer.c
/Users/jorge/prog/drqueue/libdrqueue/request.c
/Users/jorge/prog/drqueue/libdrqueue/semaphores.c
/Users/jorge/prog/drqueue/libdrqueue/shakesg.c
/Users/jorge/prog/drqueue/libdrqueue/task.c
/Users/jorge/prog/drqueue/libdrqueue/terragensg.c
/Users/jorge/prog/drqueue/libdrqueue/turtlesg.c
/Users/jorge/prog/drqueue/libdrqueue/vraysg.c
/Users/jorge/prog/drqueue/libdrqueue/xsisg.c
/Users/jorge/prog/drqueue/python/libdrqueue/3delightsg.c
/Users/jorge/prog/drqueue/python/libdrqueue/3dsmaxsg.c
src/PyDrQueue.egg-info/PKG-INFO
src/PyDrQueue.egg-info/SOURCES.txt
src/PyDrQueue.egg-info/dependency_links.txt
src/PyDrQueue.egg-info/top_level.txt
