Metadata-Version: 1.0
Name: PyDrQueue
Version: 0.64.3-r0
Summary: DrQueue bindings with Python
Home-page: http://drqueue.org/
Author: Jorge Daza
Author-email: jorge@drqueue.org
License: GPL General Public License version 2
Platform: UNKNOWN
